ifcclash/__init__.py
ifcclash/__main__.py
ifcclash/ifcclash.py
ifcclash-0.8.3.dist-info/METADATA
ifcclash-0.8.3.dist-info/WHEEL
ifcclash-0.8.3.dist-info/top_level.txt
ifcclash-0.8.3.dist-info/RECORD
